{"title":"네이버 금융 ─ 뉴스 ─ 환율","url":"https://finance.naver.com/news/news_list.naver?mode=LSS3D&section_id=101&section_id2=258&section_id3=429","favicon":"https://finance.naver.com/news/favicon.ico","elements":[{"title":"탄소중립 앞장···'그린파크'로 떠오르는 환경산업연구단지","contents":"<a href=\"/news/news_read.naver?article_id=0003978321&amp;office_id=011&amp;mode=LSS3D&amp;type=0&amp;section_id=101&amp;section_id2=258&amp;section_id3=429&amp;date=20211028&amp;page=1\" title=\"탄소중립 앞장···'그린파크'로 떠오르는 환경산업연구단지\">탄소중립 앞장···'그린파크'로 떠오르는 환경산업연구단지</a>","link":"https://finance.naver.com/news/news_read.naver?article_id=0003978321&office_id=011&mode=LSS3D&type=0&section_id=101&section_id2=258&section_id3=429&date=20211028&page=1","retrieved":1635347153704},{"title":"[기고]탄소중립을 위해 플라스틱 자원순환 혁신 전략이 필요하다","contents":"<a href=\"/news/news_read.naver?article_id=0003978318&amp;office_id=011&amp;mode=LSS3D&amp;type=0&amp;section_id=101&amp;section_id2=258&amp;section_id3=429&amp;date=20211028&amp;page=1\" title=\"[기고]탄소중립을 위해 플라스틱 자원순환 혁신 전략이 필요하다\">[기고]탄소중립을 위해 플라스틱 자원순환 혁신 전략이 필요하다</a>","link":"https://finance.naver.com/news/news_read.naver?article_id=0003978318&office_id=011&mode=LSS3D&type=0&section_id=101&section_id2=258&section_id3=429&date=20211028&page=1","retrieved":1635347153706},{"title":"ESS 보조금에···4배 비싸진 태양광발전","contents":"<a href=\"/news/news_read.naver?article_id=0003978301&amp;office_id=011&amp;mode=LSS3D&amp;type=0&amp;section_id=101&amp;section_id2=258&amp;section_id3=429&amp;date=20211028&amp;page=1\" title=\"ESS 보조금에···4배 비싸진 태양광발전\">ESS 보조금에···4배 비싸진 태양광발전</a>","link":"https://finance.naver.com/news/news_read.naver?article_id=0003978301&office_id=011&mode=LSS3D&type=0&section_id=101&section_id2=258&section_id3=429&date=20211028&page=1","retrieved":1635347153707},{"title":"'솔라시도'서도 못맞춘 태양광 경제성..원전보다 11배 비싸","contents":"<a href=\"/news/news_read.naver?article_id=0003978299&amp;office_id=011&amp;mode=LSS3D&amp;type=0&amp;section_id=101&amp;section_id2=258&amp;section_id3=429&amp;date=20211028&amp;page=1\" title=\"'솔라시도'서도 못맞춘 태양광 경제성..원전보다 11배 비싸\">'솔라시도'서도 못맞춘 태양광 경제성..원전보다 11배 비싸</a>","link":"https://finance.naver.com/news/news_read.naver?article_id=0003978299&office_id=011&mode=LSS3D&type=0&section_id=101&section_id2=258&section_id3=429&date=20211028&page=1","retrieved":1635347153709},{"title":"'헝다 리스크'에 안전자산 선호…환율, 2.4원 상승 마감","contents":"<a href=\"/news/news_read.naver?article_id=0012751243&amp;office_id=001&amp;mode=LSS3D&amp;type=0&amp;section_id=101&amp;section_id2=258&amp;section_id3=429&amp;date=20211028&amp;page=1\" title=\"'헝다 리스크'에 안전자산 선호…환율, 2.4원 상승 마감\">'헝다 리스크'에 안전자산 선호…환율, 2.4원 상승 마감</a>","link":"https://finance.naver.com/news/news_read.naver?article_id=0012751243&office_id=001&mode=LSS3D&type=0&section_id=101&section_id2=258&section_id3=429&date=20211028&page=1","retrieved":1635347153710},{"title":"2030년 NDC 40% 상향안, 국무회의서 의결","contents":"<a href=\"/news/news_read.naver?article_id=0003978007&amp;office_id=011&amp;mode=LSS3D&amp;type=0&amp;section_id=101&amp;section_id2=258&amp;section_id3=429&amp;date=20211028&amp;page=1\" title=\"2030년 NDC 40% 상향안, 국무회의서 의결\">2030년 NDC 40% 상향안, 국무회의서 의결</a>","link":"https://finance.naver.com/news/news_read.naver?article_id=0003978007&office_id=011&mode=LSS3D&type=0&section_id=101&section_id2=258&section_id3=429&date=20211028&page=1","retrieved":1635347153711},{"title":"원/달러 환율 상승 출발…1,160원대 등락","contents":"<a href=\"/news/news_read.naver?article_id=0012749584&amp;office_id=001&amp;mode=LSS3D&amp;type=0&amp;section_id=101&amp;section_id2=258&amp;section_id3=429&amp;date=20211028&amp;page=1\" title=\"원/달러 환율 상승 출발…1,160원대 등락\">원/달러 환율 상승 출발…1,160원대 등락</a>","link":"https://finance.naver.com/news/news_read.naver?article_id=0012749584&office_id=001&mode=LSS3D&type=0&section_id=101&section_id2=258&section_id3=429&date=20211028&page=1","retrieved":1635347153713},{"title":"역대 최단기 299일 만에···무역액 1조달러 돌파","contents":"<a href=\"/news/news_read.naver?article_id=0003977792&amp;office_id=011&amp;mode=LSS3D&amp;type=0&amp;section_id=101&amp;section_id2=258&amp;section_id3=429&amp;date=20211028&amp;page=1\" title=\"역대 최단기 299일 만에···무역액 1조달러 돌파\">역대 최단기 299일 만에···무역액 1조달러 돌파</a>","link":"https://finance.naver.com/news/news_read.naver?article_id=0003977792&office_id=011&mode=LSS3D&type=0&section_id=101&section_id2=258&section_id3=429&date=20211028&page=1","retrieved":1635347153715},{"title":"원/달러 환율, 증시 호조에 하락…1,167.6원 마감","contents":"<a href=\"/news/news_read.naver?article_id=0012748477&amp;office_id=001&amp;mode=LSS3D&amp;type=0&amp;section_id=101&amp;section_id2=258&amp;section_id3=429&amp;date=20211028&amp;page=1\" title=\"원/달러 환율, 증시 호조에 하락…1,167.6원 마감\">원/달러 환율, 증시 호조에 하락…1,167.6원 마감</a>","link":"https://finance.naver.com/news/news_read.naver?article_id=0012748477&office_id=001&mode=LSS3D&type=0&section_id=101&section_id2=258&section_id3=429&date=20211028&page=1","retrieved":1635347153718},{"title":"299일만에 무역 1조달러 돌파···사상 최대 무역규모 전망","contents":"<a href=\"/news/news_read.naver?article_id=0003977588&amp;office_id=011&amp;mode=LSS3D&amp;type=0&amp;section_id=101&amp;section_id2=258&amp;section_id3=429&amp;date=20211028&amp;page=1\" title=\"299일만에 무역 1조달러 돌파···사상 최대 무역규모 전망\">299일만에 무역 1조달러 돌파···사상 최대 무역규모 전망</a>","link":"https://finance.naver.com/news/news_read.naver?article_id=0003977588&office_id=011&mode=LSS3D&type=0&section_id=101&section_id2=258&section_id3=429&date=20211028&page=1","retrieved":1635347153718}]}