{"title":"네이버 금융 ─ 뉴스 ─ 포토뉴스","url":"https://finance.naver.com/news/news_list.naver?mode=LSTD&section_id=101&section_id2=258&type=1","favicon":"https://finance.naver.com/news/favicon.ico","elements":[{"title":"[주식 매매 상위 종목 및 환율] 2021년 12월 10일자","contents":"조선일보","link":"https://finance.naver.com/news/news_read.naver?article_id=0003658934&office_id=023&mode=LSTD&type=1&section_id=101&section_id2=258&section_id3=&date=20211211&page=1","retrieved":1639191720000},{"title":"웰링턴 \"인플레, 생각보다 길겠지만…내년 투자환경 긍정적\"","contents":"한국경제TV","link":"https://finance.naver.com/news/news_read.naver?article_id=0001002905&office_id=215&mode=LSTD&type=1&section_id=101&section_id2=258&section_id3=&date=20211211&page=1","retrieved":1639191600000},{"title":"포스코, 결국 '물적분할' 택했다…소액주주 '최정우 비난' 봇물","contents":"더팩트","link":"https://finance.naver.com/news/news_read.naver?article_id=0000121074&office_id=629&mode=LSTD&type=1&section_id=101&section_id2=258&section_id3=&date=20211211&page=1","retrieved":1639148699808},{"title":"[주간사모펀드] M&A 대어 '미니스톱' 온다…유력 PEF 운용사는?","contents":"더팩트","link":"https://finance.naver.com/news/news_read.naver?article_id=0000121062&office_id=629&mode=LSTD&type=1&section_id=101&section_id2=258&section_id3=&date=20211211&page=1","retrieved":1639148699809},{"title":"기록적인 인플레 지표에도 증시 상승출발·머스크 주식 또 팔았다 [뉴욕증시 나..","contents":"한국경제TV","link":"https://finance.naver.com/news/news_read.naver?article_id=0001002900&office_id=215&mode=LSTD&type=1&section_id=101&section_id2=258&section_id3=&date=20211211&page=1","retrieved":1639148699810},{"title":"SK證, 조직개편·인사 단행…IB 총괄 신설","contents":"뉴시스","link":"https://finance.naver.com/news/news_read.naver?article_id=0010883386&office_id=003&mode=LSTD&type=1&section_id=101&section_id2=258&section_id3=&date=20211211&page=1","retrieved":1639148699812},{"title":"美 11월 소비자물가 6.8% 상승… 39년 만에 최고치","contents":"조선일보","link":"https://finance.naver.com/news/news_read.naver?article_id=0003658895&office_id=023&mode=LSTD&type=1&section_id=101&section_id2=258&section_id3=&date=20211211&page=1","retrieved":1639148699813},{"title":"SK증권, IB·디지털 강화 본격화…조직개편·인사 단행","contents":"아이뉴스24","link":"https://finance.naver.com/news/news_read.naver?article_id=0000641858&office_id=031&mode=LSTD&type=1&section_id=101&section_id2=258&section_id3=&date=20211211&page=1","retrieved":1639148699814},{"title":"카카오페이 경영진, 상장 한달 만에 주식 팔아치워…주가 고점?","contents":"아이뉴스24","link":"https://finance.naver.com/news/news_read.naver?article_id=0000641855&office_id=031&mode=LSTD&type=1&section_id=101&section_id2=258&section_id3=&date=20211211&page=1","retrieved":1639148699816},{"title":"베트남 '新농업강국의 꿈', 한국 농업 장인들 초청 'K-농업기술 전수 · 교류'","contents":"한국경제TV","link":"https://finance.naver.com/news/news_read.naver?article_id=0001002890&office_id=215&mode=LSTD&type=1&section_id=101&section_id2=258&section_id3=&date=20211211&page=1","retrieved":1639148699819}]}