{"title":"네이버 금융 ─ 뉴스 ─ 실시간 속보","url":"https://finance.naver.com/news/news_list.naver?mode=LSS2D&section_id=101&section_id2=258","favicon":"https://finance.naver.com/news/favicon.ico","elements":[{"title":"\"분쟁 숨기고 5성급 호텔 팔아\"…미래에셋, 중국 안방보험에 완승","contents":"<a href=\"/news/news_read.naver?article_id=0000645855&amp;office_id=469&amp;mode=LSS2D&amp;type=0&amp;section_id=101&amp;section_id2=258&amp;section_id3=&amp;date=20211209&amp;page=1\" title=\"&quot;분쟁 숨기고 5성급 호텔 팔아&quot;…미래에셋, 중국 안방보험에 완승\">\"분쟁 숨기고 5성급 호텔 팔아\"…미래에셋, 중국 안방보험에 완승</a>","link":"https://finance.naver.com/news/news_read.naver?article_id=0000645855&office_id=469&mode=LSS2D&type=0&section_id=101&section_id2=258&section_id3=&date=20211209&page=1","retrieved":1639037226262},{"title":"탄소배출권 ETF 연일 신고가 경신···상승 흐름 이어갈까","contents":"<a href=\"/news/news_read.naver?article_id=0000641508&amp;office_id=031&amp;mode=LSS2D&amp;type=0&amp;section_id=101&amp;section_id2=258&amp;section_id3=&amp;date=20211209&amp;page=1\" title=\"탄소배출권 ETF 연일 신고가 경신···상승 흐름 이어갈까\">탄소배출권 ETF 연일 신고가 경신···상승 흐름 이어갈까</a>","link":"https://finance.naver.com/news/news_read.naver?article_id=0000641508&office_id=031&mode=LSS2D&type=0&section_id=101&section_id2=258&section_id3=&date=20211209&page=1","retrieved":1639037226263},{"title":"금융당국 “퇴직연금 디폴트 옵션 하위 규정 내년 상반기 중 마련할 것”","contents":"<a href=\"/news/news_read.naver?article_id=0000779409&amp;office_id=366&amp;mode=LSS2D&amp;type=0&amp;section_id=101&amp;section_id2=258&amp;section_id3=&amp;date=20211209&amp;page=1\" title=\"금융당국 “퇴직연금 디폴트 옵션 하위 규정 내년 상반기 중 마련할 것”\">금융당국 “퇴직연금 디폴트 옵션 하위 규정 내년 상반기 중 마련할 것”</a>","link":"https://finance.naver.com/news/news_read.naver?article_id=0000779409&office_id=366&mode=LSS2D&type=0&section_id=101&section_id2=258&section_id3=&date=20211209&page=1","retrieved":1639037226264},{"title":"[fn마감시황] 기관 매수에 코스피 3020선으로...코스닥도 상승","contents":"<a href=\"/news/news_read.naver?article_id=0004753284&amp;office_id=014&amp;mode=LSS2D&amp;type=0&amp;section_id=101&amp;section_id2=258&amp;section_id3=&amp;date=20211209&amp;page=1\" title=\"[fn마감시황] 기관 매수에 코스피 3020선으로...코스닥도 상승\">[fn마감시황] 기관 매수에 코스피 3020선으로...코스닥도 상승</a>","link":"https://finance.naver.com/news/news_read.naver?article_id=0004753284&office_id=014&mode=LSS2D&type=0&section_id=101&section_id2=258&section_id3=&date=20211209&page=1","retrieved":1639037226266},{"title":"거래소, '단일가 매매 적용 저유동성' 10종목 예비 선정","contents":"<a href=\"/news/news_read.naver?article_id=0002555968&amp;office_id=119&amp;mode=LSS2D&amp;type=0&amp;section_id=101&amp;section_id2=258&amp;section_id3=&amp;date=20211209&amp;page=1\" title=\"거래소, '단일가 매매 적용 저유동성' 10종목 예비 선정\">거래소, '단일가 매매 적용 저유동성' 10종목 예비 선정</a>","link":"https://finance.naver.com/news/news_read.naver?article_id=0002555968&office_id=119&mode=LSS2D&type=0&section_id=101&section_id2=258&section_id3=&date=20211209&page=1","retrieved":1639037226267},{"title":"넷마블 ‘활짝’ 카뱅 ‘울상’ [3분 국내주식]","contents":"<a href=\"/news/news_read.naver?article_id=0001490291&amp;office_id=005&amp;mode=LSS2D&amp;type=0&amp;section_id=101&amp;section_id2=258&amp;section_id3=&amp;date=20211209&amp;page=1\" title=\"넷마블 ‘활짝’ 카뱅 ‘울상’ [3분 국내주식]\">넷마블 ‘활짝’ 카뱅 ‘울상’ [3분 국내주식]</a>","link":"https://finance.naver.com/news/news_read.naver?article_id=0001490291&office_id=005&mode=LSS2D&type=0&section_id=101&section_id2=258&section_id3=&date=20211209&page=1","retrieved":1639037226269},{"title":"디폴트옵션 국회통과…금투협 “의미있는 연금 재원 기대”","contents":"<a href=\"/news/news_read.naver?article_id=0005103665&amp;office_id=018&amp;mode=LSS2D&amp;type=0&amp;section_id=101&amp;section_id2=258&amp;section_id3=&amp;date=20211209&amp;page=1\" title=\"디폴트옵션 국회통과…금투협 “의미있는 연금 재원 기대”\">디폴트옵션 국회통과…금투협 “의미있는 연금 재원 기대”</a>","link":"https://finance.naver.com/news/news_read.naver?article_id=0005103665&office_id=018&mode=LSS2D&type=0&section_id=101&section_id2=258&section_id3=&date=20211209&page=1","retrieved":1639037226270}]}