{"title":"네이버 금융 ─ 뉴스 ─ TV뉴스","url":"https://finance.naver.com/news/news_list.naver?mode=TV&section_id=tv","favicon":"https://finance.naver.com/news/favicon.ico","elements":[{"title":"삼성화재 '갤럭시북'‥내부거래에 낀 회사 정체는?","contents":"MBC","link":"https://finance.naver.com/news/news_read.naver?article_id=0001153916&office_id=214&mode=TV&type=2&section_id=115&section_id2=292&section_id3=&date=20211015&page=1","retrieved":1634280240000},{"title":"정의선 회장 1년…미래 모빌리티 악셀·수소경제 선도","contents":"SBS Biz","link":"https://finance.naver.com/news/news_read.naver?article_id=0000260827&office_id=374&mode=TV&type=2&section_id=115&section_id2=292&section_id3=&date=20211015&page=1","retrieved":1634280120000},{"title":"실수요자 반발에… “전세·잔금대출 중단 없다”","contents":"SBS Biz","link":"https://finance.naver.com/news/news_read.naver?article_id=0000260826&office_id=374&mode=TV&type=2&section_id=115&section_id2=292&section_id3=&date=20211015&page=1","retrieved":1634280060000},{"title":"[신선한 경제] 잘 몰라서‥ '에너지바우처' 미사용 금액 373억 원","contents":"MBC","link":"https://finance.naver.com/news/news_read.naver?article_id=0001153915&office_id=214&mode=TV&type=2&section_id=115&section_id2=292&section_id3=&date=20211015&page=1","retrieved":1634280000000},{"title":"실수요자 피해 우려에 전세대출 중단 없을 듯","contents":"KBS","link":"https://finance.naver.com/news/news_read.naver?article_id=0011137898&office_id=056&mode=TV&type=2&section_id=115&section_id2=292&section_id3=&date=20211015&page=1","retrieved":1634280000000},{"title":"[신선한 경제] 인감도장 대신 '본인 서명'하세요","contents":"MBC","link":"https://finance.naver.com/news/news_read.naver?article_id=0001153914&office_id=214&mode=TV&type=2&section_id=115&section_id2=292&section_id3=&date=20211015&page=1","retrieved":1634280000000},{"title":"[신선한 경제] 한 봉지 380원 vs 2,200원‥ 라면 값도 양극화","contents":"MBC","link":"https://finance.naver.com/news/news_read.naver?article_id=0001153913&office_id=214&mode=TV&type=2&section_id=115&section_id2=292&section_id3=&date=20211015&page=1","retrieved":1634279940000},{"title":"[신선한 경제] 빚내 산 '깡통주택'으로 보증보험 가입","contents":"MBC","link":"https://finance.naver.com/news/news_read.naver?article_id=0001153912&office_id=214&mode=TV&type=2&section_id=115&section_id2=292&section_id3=&date=20211015&page=1","retrieved":1634279820000},{"title":"늘어난 서울 아파트 하락 거래…시장 변화 조짐","contents":"KBS","link":"https://finance.naver.com/news/news_read.naver?article_id=0011137897&office_id=056&mode=TV&type=2&section_id=115&section_id2=292&section_id3=&date=20211015&page=1","retrieved":1634279820000},{"title":"치솟는 G2 물가…커지는 ‘인플레 쇼크’ 우려 [장가희 기자의 뉴스픽]","contents":"SBS Biz","link":"https://finance.naver.com/news/news_read.naver?article_id=0000260822&office_id=374&mode=TV&type=2&section_id=115&section_id2=292&section_id3=&date=20211015&page=1","retrieved":1634279580000}]}