{"title":"네이버 금융 ─ 뉴스 ─ 해외증시","url":"https://finance.naver.com/news/news_list.naver?mode=LSS3D&section_id=101&section_id2=258&section_id3=403","favicon":"https://finance.naver.com/news/favicon.ico","elements":[{"title":"\"메타버스에 베팅하고 싶다면 이 3가지 종목을 주목하라\"","contents":"<a href=\"/news/news_read.naver?article_id=0000994699&amp;office_id=215&amp;mode=LSS3D&amp;type=0&amp;section_id=101&amp;section_id2=258&amp;section_id3=403&amp;date=20211104&amp;page=1\" title=\"&quot;메타버스에 베팅하고 싶다면 이 3가지 종목을 주목하라&quot;\">\"메타버스에 베팅하고 싶다면 이 3가지 종목을 주목하라\"</a>","link":"https://finance.naver.com/news/news_read.naver?article_id=0000994699&office_id=215&mode=LSS3D&type=0&section_id=101&section_id2=258&section_id3=403&date=20211104&page=1","retrieved":1635985135181},{"title":"[표]해외DR 가격(11월 3일)","contents":"<a href=\"/news/news_read.naver?article_id=0003981292&amp;office_id=011&amp;mode=LSS3D&amp;type=0&amp;section_id=101&amp;section_id2=258&amp;section_id3=403&amp;date=20211104&amp;page=1\" title=\"[표]해외DR 가격(11월 3일)\">[표]해외DR 가격(11월 3일)</a>","link":"https://finance.naver.com/news/news_read.naver?article_id=0003981292&office_id=011&mode=LSS3D&type=0&section_id=101&section_id2=258&section_id3=403&date=20211104&page=1","retrieved":1635985135181},{"title":"\"한 달만에 또?\"…페이스북·인스타 메신저 '먹통'","contents":"<a href=\"/news/news_read.naver?article_id=0000994696&amp;office_id=215&amp;mode=LSS3D&amp;type=0&amp;section_id=101&amp;section_id2=258&amp;section_id3=403&amp;date=20211104&amp;page=1\" title=\"&quot;한 달만에 또?&quot;…페이스북·인스타 메신저 '먹통'\">\"한 달만에 또?\"…페이스북·인스타 메신저 '먹통'</a>","link":"https://finance.naver.com/news/news_read.naver?article_id=0000994696&office_id=215&mode=LSS3D&type=0&section_id=101&section_id2=258&section_id3=403&date=20211104&page=1","retrieved":1635985135181},{"title":"[표]해외 주요 증시 동향(11월 3일)","contents":"<a href=\"/news/news_read.naver?article_id=0003981291&amp;office_id=011&amp;mode=LSS3D&amp;type=0&amp;section_id=101&amp;section_id2=258&amp;section_id3=403&amp;date=20211104&amp;page=1\" title=\"[표]해외 주요 증시 동향(11월 3일)\">[표]해외 주요 증시 동향(11월 3일)</a>","link":"https://finance.naver.com/news/news_read.naver?article_id=0003981291&office_id=011&mode=LSS3D&type=0&section_id=101&section_id2=258&section_id3=403&date=20211104&page=1","retrieved":1635985135182},{"title":"[외환브리핑]테이퍼링에도 파월은 비둘기…하루 만에 1170원대 복귀 시도","contents":"<a href=\"/news/news_read.naver?article_id=0005077608&amp;office_id=018&amp;mode=LSS3D&amp;type=0&amp;section_id=101&amp;section_id2=258&amp;section_id3=403&amp;date=20211104&amp;page=1\" title=\"[외환브리핑]테이퍼링에도 파월은 비둘기…하루 만에 1170원대 복귀 시도\">[외환브리핑]테이퍼링에도 파월은 비둘기…하루 만에 1170원대 복귀 시도</a>","link":"https://finance.naver.com/news/news_read.naver?article_id=0005077608&office_id=018&mode=LSS3D&type=0&section_id=101&section_id2=258&section_id3=403&date=20211104&page=1","retrieved":1635985135183},{"title":"[표]해외 한국 DR(11/3)","contents":"<a href=\"/news/news_read.naver?article_id=0005077593&amp;office_id=018&amp;mode=LSS3D&amp;type=0&amp;section_id=101&amp;section_id2=258&amp;section_id3=403&amp;date=20211104&amp;page=1\" title=\"[표]해외 한국 DR(11/3)\">[표]해외 한국 DR(11/3)</a>","link":"https://finance.naver.com/news/news_read.naver?article_id=0005077593&office_id=018&mode=LSS3D&type=0&section_id=101&section_id2=258&section_id3=403&date=20211104&page=1","retrieved":1635985135185},{"title":"美 부동산업체 질로우 사흘째 급락...돈나무 언니는 '줍줍'","contents":"<a href=\"/news/news_read.naver?article_id=0000994690&amp;office_id=215&amp;mode=LSS3D&amp;type=0&amp;section_id=101&amp;section_id2=258&amp;section_id3=403&amp;date=20211104&amp;page=1\" title=\"美 부동산업체 질로우 사흘째 급락...돈나무 언니는 '줍줍'\">美 부동산업체 질로우 사흘째 급락...돈나무 언니는 '줍줍'</a>","link":"https://finance.naver.com/news/news_read.naver?article_id=0000994690&office_id=215&mode=LSS3D&type=0&section_id=101&section_id2=258&section_id3=403&date=20211104&page=1","retrieved":1635985135187}]}