{"title":"네이버 금융 ─ 뉴스 ─ 해외증시","url":"https://finance.naver.com/news/news_list.naver?mode=LSS3D&section_id=101&section_id2=258&section_id3=403","favicon":"https://finance.naver.com/news/favicon.ico","elements":[{"title":"中 투자자, 오징어게임 코인 투자했다 전재산 날려","contents":"<a href=\"/news/news_read.naver?article_id=0000994422&amp;office_id=215&amp;mode=LSS3D&amp;type=0&amp;section_id=101&amp;section_id2=258&amp;section_id3=403&amp;date=20211103&amp;page=1\" title=\"中 투자자, 오징어게임 코인 투자했다 전재산 날려\">中 투자자, 오징어게임 코인 투자했다 전재산 날려</a>","link":"https://finance.naver.com/news/news_read.naver?article_id=0000994422&office_id=215&mode=LSS3D&type=0&section_id=101&section_id2=258&section_id3=403&date=20211103&page=1","retrieved":1635898734047},{"title":"[표]해외 DR 가격(11월 2일)","contents":"<a href=\"/news/news_read.naver?article_id=0003980796&amp;office_id=011&amp;mode=LSS3D&amp;type=0&amp;section_id=101&amp;section_id2=258&amp;section_id3=403&amp;date=20211103&amp;page=1\" title=\"[표]해외 DR 가격(11월 2일)\">[표]해외 DR 가격(11월 2일)</a>","link":"https://finance.naver.com/news/news_read.naver?article_id=0003980796&office_id=011&mode=LSS3D&type=0&section_id=101&section_id2=258&section_id3=403&date=20211103&page=1","retrieved":1635898734048},{"title":"[표]해외 주요 증시 동향(11월 2일)","contents":"<a href=\"/news/news_read.naver?article_id=0003980794&amp;office_id=011&amp;mode=LSS3D&amp;type=0&amp;section_id=101&amp;section_id2=258&amp;section_id3=403&amp;date=20211103&amp;page=1\" title=\"[표]해외 주요 증시 동향(11월 2일)\">[표]해외 주요 증시 동향(11월 2일)</a>","link":"https://finance.naver.com/news/news_read.naver?article_id=0003980794&office_id=011&mode=LSS3D&type=0&section_id=101&section_id2=258&section_id3=403&date=20211103&page=1","retrieved":1635898734050},{"title":"[외환브리핑]FOMC 회의 시작되자 달러강세…환율, 1180원 상승 시도","contents":"<a href=\"/news/news_read.naver?article_id=0005076604&amp;office_id=018&amp;mode=LSS3D&amp;type=0&amp;section_id=101&amp;section_id2=258&amp;section_id3=403&amp;date=20211103&amp;page=1\" title=\"[외환브리핑]FOMC 회의 시작되자 달러강세…환율, 1180원 상승 시도\">[외환브리핑]FOMC 회의 시작되자 달러강세…환율, 1180원 상승 시도</a>","link":"https://finance.naver.com/news/news_read.naver?article_id=0005076604&office_id=018&mode=LSS3D&type=0&section_id=101&section_id2=258&section_id3=403&date=20211103&page=1","retrieved":1635898734051},{"title":"제프 베이조스 \"환경보호 위해 2조원 내놓겠다\"","contents":"<a href=\"/news/news_read.naver?article_id=0000994409&amp;office_id=215&amp;mode=LSS3D&amp;type=0&amp;section_id=101&amp;section_id2=258&amp;section_id3=403&amp;date=20211103&amp;page=1\" title=\"제프 베이조스 &quot;환경보호 위해 2조원 내놓겠다&quot;\">제프 베이조스 \"환경보호 위해 2조원 내놓겠다\"</a>","link":"https://finance.naver.com/news/news_read.naver?article_id=0000994409&office_id=215&mode=LSS3D&type=0&section_id=101&section_id2=258&section_id3=403&date=20211103&page=1","retrieved":1635894253797},{"title":"[표]해외 한국 DR(11/2)","contents":"<a href=\"/news/news_read.naver?article_id=0005076592&amp;office_id=018&amp;mode=LSS3D&amp;type=0&amp;section_id=101&amp;section_id2=258&amp;section_id3=403&amp;date=20211103&amp;page=1\" title=\"[표]해외 한국 DR(11/2)\">[표]해외 한국 DR(11/2)</a>","link":"https://finance.naver.com/news/news_read.naver?article_id=0005076592&office_id=018&mode=LSS3D&type=0&section_id=101&section_id2=258&section_id3=403&date=20211103&page=1","retrieved":1635894253798},{"title":"[표]미국 주요기업 주가(11/2)","contents":"<a href=\"/news/news_read.naver?article_id=0005076579&amp;office_id=018&amp;mode=LSS3D&amp;type=0&amp;section_id=101&amp;section_id2=258&amp;section_id3=403&amp;date=20211103&amp;page=1\" title=\"[표]미국 주요기업 주가(11/2)\">[표]미국 주요기업 주가(11/2)</a>","link":"https://finance.naver.com/news/news_read.naver?article_id=0005076579&office_id=018&mode=LSS3D&type=0&section_id=101&section_id2=258&section_id3=403&date=20211103&page=1","retrieved":1635894253805},{"title":"뉴욕증시, 주요지수 사흘째 사상 최고치…기업들 호실적에 '훈풍'","contents":"<a href=\"/news/news_read.naver?article_id=0004623860&amp;office_id=015&amp;mode=LSS3D&amp;type=0&amp;section_id=101&amp;section_id2=258&amp;section_id3=403&amp;date=20211103&amp;page=1\" title=\"뉴욕증시, 주요지수 사흘째 사상 최고치…기업들 호실적에 '훈풍'\">뉴욕증시, 주요지수 사흘째 사상 최고치…기업들 호실적에 '훈풍'</a>","link":"https://finance.naver.com/news/news_read.naver?article_id=0004623860&office_id=015&mode=LSS3D&type=0&section_id=101&section_id2=258&section_id3=403&date=20211103&page=1","retrieved":1635894253806}]}