{"title":"네이버 금융 ─ 뉴스 ─ 실시간 속보","url":"https://finance.naver.com/news/news_list.naver?mode=LSS2D&section_id=101&section_id2=258","favicon":"https://finance.naver.com/news/favicon.ico","elements":[{"title":"[fn마켓워치]강원랜드, 2000억 규모 OCIO에 ‘NH證·미래에셋운용’","contents":"<a href=\"/news/news_read.naver?article_id=0004744078&amp;office_id=014&amp;mode=LSS2D&amp;type=0&amp;section_id=101&amp;section_id2=258&amp;section_id3=&amp;date=20211123&amp;page=1\" title=\"[fn마켓워치]강원랜드, 2000억 규모 OCIO에 ‘NH證·미래에셋운용’\">[fn마켓워치]강원랜드, 2000억 규모 OCIO에 ‘NH證·미래에셋운용’</a>","link":"https://finance.naver.com/news/news_read.naver?article_id=0004744078&office_id=014&mode=LSS2D&type=0&section_id=101&section_id2=258&section_id3=&date=20211123&page=1","retrieved":1637632080830},{"title":"[fn마켓워치]지노바인베, 온라인 담보대출 '베스트핀'에 투자","contents":"<a href=\"/news/news_read.naver?article_id=0004744076&amp;office_id=014&amp;mode=LSS2D&amp;type=0&amp;section_id=101&amp;section_id2=258&amp;section_id3=&amp;date=20211123&amp;page=1\" title=\"[fn마켓워치]지노바인베, 온라인 담보대출 '베스트핀'에 투자\">[fn마켓워치]지노바인베, 온라인 담보대출 '베스트핀'에 투자</a>","link":"https://finance.naver.com/news/news_read.naver?article_id=0004744076&office_id=014&mode=LSS2D&type=0&section_id=101&section_id2=258&section_id3=&date=20211123&page=1","retrieved":1637632080830},{"title":"[특징주] NFT 타고 날았던 위메이드·카겜 등 게임株, 이틀 연속 약세","contents":"<a href=\"/news/news_read.naver?article_id=0003988376&amp;office_id=011&amp;mode=LSS2D&amp;type=0&amp;section_id=101&amp;section_id2=258&amp;section_id3=&amp;date=20211123&amp;page=1\" title=\"[특징주] NFT 타고 날았던 위메이드·카겜 등 게임株, 이틀 연속 약세\">[특징주] NFT 타고 날았던 위메이드·카겜 등 게임株, 이틀 연속 약세</a>","link":"https://finance.naver.com/news/news_read.naver?article_id=0003988376&office_id=011&mode=LSS2D&type=0&section_id=101&section_id2=258&section_id3=&date=20211123&page=1","retrieved":1637632080830},{"title":"금융위 \"셀트리온 감리 진행중\"…셀트리온 3형제 동반 급락","contents":"<a href=\"/news/news_read.naver?article_id=0004882970&amp;office_id=009&amp;mode=LSS2D&amp;type=0&amp;section_id=101&amp;section_id2=258&amp;section_id3=&amp;date=20211123&amp;page=1\" title=\"금융위 &quot;셀트리온 감리 진행중&quot;…셀트리온 3형제 동반 급락\">금융위 \"셀트리온 감리 진행중\"…셀트리온 3형제 동반 급락</a>","link":"https://finance.naver.com/news/news_read.naver?article_id=0004882970&office_id=009&mode=LSS2D&type=0&section_id=101&section_id2=258&section_id3=&date=20211123&page=1","retrieved":1637632080830},{"title":"[fn마켓워치]MBK, 올해 한·중·일 엑시트 성공..16년 만","contents":"<a href=\"/news/news_read.naver?article_id=0004744070&amp;office_id=014&amp;mode=LSS2D&amp;type=0&amp;section_id=101&amp;section_id2=258&amp;section_id3=&amp;date=20211123&amp;page=1\" title=\"[fn마켓워치]MBK, 올해 한·중·일 엑시트 성공..16년 만\">[fn마켓워치]MBK, 올해 한·중·일 엑시트 성공..16년 만</a>","link":"https://finance.naver.com/news/news_read.naver?article_id=0004744070&office_id=014&mode=LSS2D&type=0&section_id=101&section_id2=258&section_id3=&date=20211123&page=1","retrieved":1637632080830},{"title":"동탄 트램 및 인동선 서천역 예정 ‘신동탄 헤센IT타워’ 지식산업센터 내 상업시설 공급 안..","contents":"<a href=\"/news/news_read.naver?article_id=0003988371&amp;office_id=011&amp;mode=LSS2D&amp;type=0&amp;section_id=101&amp;section_id2=258&amp;section_id3=&amp;date=20211123&amp;page=1\" title=\"동탄 트램 및 인동선 서천역 예정 ‘신동탄 헤센IT타워’ 지식산업센터 내 상업시설 공급 안내\">동탄 트램 및 인동선 서천역 예정 ‘신동탄 헤센IT타워’ 지식산업센터 내 상업시설 공급 안..</a>","link":"https://finance.naver.com/news/news_read.naver?article_id=0003988371&office_id=011&mode=LSS2D&type=0&section_id=101&section_id2=258&section_id3=&date=20211123&page=1","retrieved":1637632080834},{"title":"코스피, 기관 '팔자'에 낙폭 확대…장중 3000선 밑돌아","contents":"<a href=\"/news/news_read.naver?article_id=0005091977&amp;office_id=018&amp;mode=LSS2D&amp;type=0&amp;section_id=101&amp;section_id2=258&amp;section_id3=&amp;date=20211123&amp;page=1\" title=\"코스피, 기관 '팔자'에 낙폭 확대…장중 3000선 밑돌아\">코스피, 기관 '팔자'에 낙폭 확대…장중 3000선 밑돌아</a>","link":"https://finance.naver.com/news/news_read.naver?article_id=0005091977&office_id=018&mode=LSS2D&type=0&section_id=101&section_id2=258&section_id3=&date=20211123&page=1","retrieved":1637632080856},{"title":"채권전문가 90% “25일 금통위, 기준금리 인상 전망”","contents":"<a href=\"/news/news_read.naver?article_id=0002550589&amp;office_id=119&amp;mode=LSS2D&amp;type=0&amp;section_id=101&amp;section_id2=258&amp;section_id3=&amp;date=20211123&amp;page=1\" title=\"채권전문가 90% “25일 금통위, 기준금리 인상 전망”\">채권전문가 90% “25일 금통위, 기준금리 인상 전망”</a>","link":"https://finance.naver.com/news/news_read.naver?article_id=0002550589&office_id=119&mode=LSS2D&type=0&section_id=101&section_id2=258&section_id3=&date=20211123&page=1","retrieved":1637632080856},{"title":"250만호 주택공약에 건설주 화색...KT·우리넷 등 통신장비 수혜","contents":"<a href=\"/news/news_read.naver?article_id=0004744064&amp;office_id=014&amp;mode=LSS2D&amp;type=0&amp;section_id=101&amp;section_id2=258&amp;section_id3=&amp;date=20211123&amp;page=1\" title=\"250만호 주택공약에 건설주 화색...KT·우리넷 등 통신장비 수혜\">250만호 주택공약에 건설주 화색...KT·우리넷 등 통신장비 수혜</a>","link":"https://finance.naver.com/news/news_read.naver?article_id=0004744064&office_id=014&mode=LSS2D&type=0&section_id=101&section_id2=258&section_id3=&date=20211123&page=1","retrieved":1637632080856}]}