{"title":"네이버 금융 ─ 뉴스 ─ 실시간 속보","url":"https://finance.naver.com/news/news_list.naver?mode=LSS2D&section_id=101&section_id2=258","favicon":"https://finance.naver.com/news/favicon.ico","elements":[{"title":"[클릭e종목]\"현대글로비스, 글로벌 물류대란 수혜로 실적 호조\"","contents":"<a href=\"/news/news_read.naver?article_id=0004982772&amp;office_id=277&amp;mode=LSS2D&amp;type=0&amp;section_id=101&amp;section_id2=258&amp;section_id3=&amp;date=20211014&amp;page=1\" title=\"[클릭e종목]&quot;현대글로비스, 글로벌 물류대란 수혜로 실적 호조&quot;\">[클릭e종목]\"현대글로비스, 글로벌 물류대란 수혜로 실적 호조\"</a>","link":"https://finance.naver.com/news/news_read.naver?article_id=0004982772&office_id=277&mode=LSS2D&type=0&section_id=101&section_id2=258&section_id3=&date=20211014&page=1","retrieved":1634164423392},{"title":"제일기획, 국내외 성장세…실적 개선 흐름 지속 전망-키움","contents":"<a href=\"/news/news_read.naver?article_id=0005059623&amp;office_id=018&amp;mode=LSS2D&amp;type=0&amp;section_id=101&amp;section_id2=258&amp;section_id3=&amp;date=20211014&amp;page=1\" title=\"제일기획, 국내외 성장세…실적 개선 흐름 지속 전망-키움\">제일기획, 국내외 성장세…실적 개선 흐름 지속 전망-키움</a>","link":"https://finance.naver.com/news/news_read.naver?article_id=0005059623&office_id=018&mode=LSS2D&type=0&section_id=101&section_id2=258&section_id3=&date=20211014&page=1","retrieved":1634164223691},{"title":"테이퍼링 전략 내놓은 연준···속도에 주목 [글로벌마켓 A/S]","contents":"<a href=\"/news/news_read.naver?article_id=0000990087&amp;office_id=215&amp;mode=LSS2D&amp;type=0&amp;section_id=101&amp;section_id2=258&amp;section_id3=&amp;date=20211014&amp;page=1\" title=\"테이퍼링 전략 내놓은 연준···속도에 주목 [글로벌마켓 A/S]\">테이퍼링 전략 내놓은 연준···속도에 주목 [글로벌마켓 A/S]</a>","link":"https://finance.naver.com/news/news_read.naver?article_id=0000990087&office_id=215&mode=LSS2D&type=0&section_id=101&section_id2=258&section_id3=&date=20211014&page=1","retrieved":1634164223692},{"title":"[클릭 e종목]\"한파 오며 가격 추가 인상\"…한국가스공사 목표가 40%↑","contents":"<a href=\"/news/news_read.naver?article_id=0004982764&amp;office_id=277&amp;mode=LSS2D&amp;type=0&amp;section_id=101&amp;section_id2=258&amp;section_id3=&amp;date=20211014&amp;page=1\" title=\"[클릭 e종목]&quot;한파 오며 가격 추가 인상&quot;…한국가스공사 목표가 40%↑\">[클릭 e종목]\"한파 오며 가격 추가 인상\"…한국가스공사 목표가 40%↑</a>","link":"https://finance.naver.com/news/news_read.naver?article_id=0004982764&office_id=277&mode=LSS2D&type=0&section_id=101&section_id2=258&section_id3=&date=20211014&page=1","retrieved":1634164223692},{"title":"제약바이오업계, '남다른' 사회 공헌 나서는 이유","contents":"<a href=\"/news/news_read.naver?article_id=0000004214&amp;office_id=648&amp;mode=LSS2D&amp;type=0&amp;section_id=101&amp;section_id2=258&amp;section_id3=&amp;date=20211014&amp;page=1\" title=\"제약바이오업계, '남다른' 사회 공헌 나서는 이유\">제약바이오업계, '남다른' 사회 공헌 나서는 이유</a>","link":"https://finance.naver.com/news/news_read.naver?article_id=0000004214&office_id=648&mode=LSS2D&type=0&section_id=101&section_id2=258&section_id3=&date=20211014&page=1","retrieved":1634164223694},{"title":"[클릭 e종목]레이, 저점 매수 유효…확실한 실적 모멘텀","contents":"<a href=\"/news/news_read.naver?article_id=0004982762&amp;office_id=277&amp;mode=LSS2D&amp;type=0&amp;section_id=101&amp;section_id2=258&amp;section_id3=&amp;date=20211014&amp;page=1\" title=\"[클릭 e종목]레이, 저점 매수 유효…확실한 실적 모멘텀\">[클릭 e종목]레이, 저점 매수 유효…확실한 실적 모멘텀</a>","link":"https://finance.naver.com/news/news_read.naver?article_id=0004982762&office_id=277&mode=LSS2D&type=0&section_id=101&section_id2=258&section_id3=&date=20211014&page=1","retrieved":1634164223695},{"title":"[승계본색]이수건설 1대주주였던 안방마님, 주식 포기한 까닭","contents":"<a href=\"/news/news_read.naver?article_id=0000004213&amp;office_id=648&amp;mode=LSS2D&amp;type=0&amp;section_id=101&amp;section_id2=258&amp;section_id3=&amp;date=20211014&amp;page=1\" title=\"[승계본색]이수건설 1대주주였던 안방마님, 주식 포기한 까닭\">[승계본색]이수건설 1대주주였던 안방마님, 주식 포기한 까닭</a>","link":"https://finance.naver.com/news/news_read.naver?article_id=0000004213&office_id=648&mode=LSS2D&type=0&section_id=101&section_id2=258&section_id3=&date=20211014&page=1","retrieved":1634163618599},{"title":"“몰누피라비르, 시장 판도 바꾸나”… 비코로나株에 주목할 때","contents":"<a href=\"/news/news_read.naver?article_id=0004616030&amp;office_id=015&amp;mode=LSS2D&amp;type=0&amp;section_id=101&amp;section_id2=258&amp;section_id3=&amp;date=20211014&amp;page=1\" title=\"“몰누피라비르, 시장 판도 바꾸나”… 비코로나株에 주목할 때\">“몰누피라비르, 시장 판도 바꾸나”… 비코로나株에 주목할 때</a>","link":"https://finance.naver.com/news/news_read.naver?article_id=0004616030&office_id=015&mode=LSS2D&type=0&section_id=101&section_id2=258&section_id3=&date=20211014&page=1","retrieved":1634163618599}]}