{"title":"네이버 금융 ─ 뉴스 ─ 포토뉴스","url":"https://finance.naver.com/news/news_list.naver?mode=LSTD&section_id=101&section_id2=258&type=1","favicon":"https://finance.naver.com/news/favicon.ico","elements":[{"title":"포스코 지주사 전환, 주총이 관건","contents":"동아일보","link":"https://finance.naver.com/news/news_read.naver?article_id=0003399261&office_id=020&mode=LSTD&type=1&section_id=101&section_id2=258&section_id3=&date=20211213&page=1","retrieved":1639364520000},{"title":"'3개월새 300% 폭등'…잘 나가는 게임주 진짜 보석은?","contents":"이데일리","link":"https://finance.naver.com/news/news_read.naver?article_id=0005105075&office_id=018&mode=LSTD&type=1&section_id=101&section_id2=258&section_id3=&date=20211213&page=1","retrieved":1639359060000},{"title":"연말 배당주 막차 탈 시간…언제 사고 언제 팔까","contents":"이데일리","link":"https://finance.naver.com/news/news_read.naver?article_id=0005105073&office_id=018&mode=LSTD&type=1&section_id=101&section_id2=258&section_id3=&date=20211213&page=1","retrieved":1639325229345},{"title":"[표] 주간 주요 증시 지표","contents":"매일경제","link":"https://finance.naver.com/news/news_read.naver?article_id=0004892747&office_id=009&mode=LSTD&type=1&section_id=101&section_id2=258&section_id3=&date=20211213&page=1","retrieved":1639321516255},{"title":"SGI서울보증, `고가 전세` 대출보증 중단 안 한다...\"현행처럼 제공\"","contents":"디지털타임스","link":"https://finance.naver.com/news/news_read.naver?article_id=0002710622&office_id=029&mode=LSTD&type=1&section_id=101&section_id2=258&section_id3=&date=20211213&page=1","retrieved":1639321516258},{"title":"홍콩 투자 개미들은 물렸다... 순매수 상위 5개 종목 봤더니","contents":"조선일보","link":"https://finance.naver.com/news/news_read.naver?article_id=0003659119&office_id=023&mode=LSTD&type=1&section_id=101&section_id2=258&section_id3=&date=20211213&page=1","retrieved":1639321516260},{"title":"정부·국회, 카드 수수료 인하안 막판 조율중","contents":"디지털타임스","link":"https://finance.naver.com/news/news_read.naver?article_id=0002710574&office_id=029&mode=LSTD&type=1&section_id=101&section_id2=258&section_id3=&date=20211213&page=1","retrieved":1639321516261},{"title":"반도체주 상승 1위","contents":"디지털타임스","link":"https://finance.naver.com/news/news_read.naver?article_id=0002710582&office_id=029&mode=LSTD&type=1&section_id=101&section_id2=258&section_id3=&date=20211213&page=1","retrieved":1639321516263},{"title":"자리잡는 코인거래소, 공직자까지 모셔간다","contents":"디지털타임스","link":"https://finance.naver.com/news/news_read.naver?article_id=0002710581&office_id=029&mode=LSTD&type=1&section_id=101&section_id2=258&section_id3=&date=20211213&page=1","retrieved":1639321516264},{"title":"한투 개발 `키스라` 테스트베드 심사 통과","contents":"디지털타임스","link":"https://finance.naver.com/news/news_read.naver?article_id=0002710580&office_id=029&mode=LSTD&type=1&section_id=101&section_id2=258&section_id3=&date=20211213&page=1","retrieved":1639321516265}]}