{"title":"네이버 금융 ─ 뉴스 ─ 해외증시","url":"https://finance.naver.com/news/news_list.naver?mode=LSS3D&section_id=101&section_id2=258&section_id3=403","favicon":"https://finance.naver.com/news/favicon.ico","elements":[{"title":"[표]해외 주요 증시 동향(11월 22일)","contents":"<a href=\"/news/news_read.naver?article_id=0003988288&amp;office_id=011&amp;mode=LSS3D&amp;type=0&amp;section_id=101&amp;section_id2=258&amp;section_id3=403&amp;date=20211123&amp;page=1\" title=\"[표]해외 주요 증시 동향(11월 22일)\">[표]해외 주요 증시 동향(11월 22일)</a>","link":"https://finance.naver.com/news/news_read.naver?article_id=0003988288&office_id=011&mode=LSS3D&type=0&section_id=101&section_id2=258&section_id3=403&date=20211123&page=1","retrieved":1637626781948},{"title":"[표]해외DR 가격(11월 22일)","contents":"<a href=\"/news/news_read.naver?article_id=0003988284&amp;office_id=011&amp;mode=LSS3D&amp;type=0&amp;section_id=101&amp;section_id2=258&amp;section_id3=403&amp;date=20211123&amp;page=1\" title=\"[표]해외DR 가격(11월 22일)\">[표]해외DR 가격(11월 22일)</a>","link":"https://finance.naver.com/news/news_read.naver?article_id=0003988284&office_id=011&mode=LSS3D&type=0&section_id=101&section_id2=258&section_id3=403&date=20211123&page=1","retrieved":1637626781949},{"title":"[표]해외DR 가격(11월 22일)","contents":"<a href=\"/news/news_read.naver?article_id=0003988283&amp;office_id=011&amp;mode=LSS3D&amp;type=0&amp;section_id=101&amp;section_id2=258&amp;section_id3=403&amp;date=20211123&amp;page=1\" title=\"[표]해외DR 가격(11월 22일)\">[표]해외DR 가격(11월 22일)</a>","link":"https://finance.naver.com/news/news_read.naver?article_id=0003988283&office_id=011&mode=LSS3D&type=0&section_id=101&section_id2=258&section_id3=403&date=20211123&page=1","retrieved":1637626781949},{"title":"올해 IPO 기대주, 금리인상 불안감 속 일제히 급락","contents":"<a href=\"/news/news_read.naver?article_id=0000998652&amp;office_id=215&amp;mode=LSS3D&amp;type=0&amp;section_id=101&amp;section_id2=258&amp;section_id3=403&amp;date=20211123&amp;page=1\" title=\"올해 IPO 기대주, 금리인상 불안감 속 일제히 급락\">올해 IPO 기대주, 금리인상 불안감 속 일제히 급락</a>","link":"https://finance.naver.com/news/news_read.naver?article_id=0000998652&office_id=215&mode=LSS3D&type=0&section_id=101&section_id2=258&section_id3=403&date=20211123&page=1","retrieved":1637626781952},{"title":"백신 의무접종 D-Day, 美공무원 90% 이상 접종 완료","contents":"<a href=\"/news/news_read.naver?article_id=0000998648&amp;office_id=215&amp;mode=LSS3D&amp;type=0&amp;section_id=101&amp;section_id2=258&amp;section_id3=403&amp;date=20211123&amp;page=1\" title=\"백신 의무접종 D-Day, 美공무원 90% 이상 접종 완료\">백신 의무접종 D-Day, 美공무원 90% 이상 접종 완료</a>","link":"https://finance.naver.com/news/news_read.naver?article_id=0000998648&office_id=215&mode=LSS3D&type=0&section_id=101&section_id2=258&section_id3=403&date=20211123&page=1","retrieved":1637626781954},{"title":"\"별점 리뷰 테러할 것\"…JP모건 소송제기에 뿔난 머스크","contents":"<a href=\"/news/news_read.naver?article_id=0000998641&amp;office_id=215&amp;mode=LSS3D&amp;type=0&amp;section_id=101&amp;section_id2=258&amp;section_id3=403&amp;date=20211123&amp;page=1\" title=\"&quot;별점 리뷰 테러할 것&quot;…JP모건 소송제기에 뿔난 머스크\">\"별점 리뷰 테러할 것\"…JP모건 소송제기에 뿔난 머스크</a>","link":"https://finance.naver.com/news/news_read.naver?article_id=0000998641&office_id=215&mode=LSS3D&type=0&section_id=101&section_id2=258&section_id3=403&date=20211123&page=1","retrieved":1637626781955},{"title":"[외환브리핑]팬데믹 재확산+연준 긴축 우려…환율, 1190원대 상승 재시도","contents":"<a href=\"/news/news_read.naver?article_id=0005091756&amp;office_id=018&amp;mode=LSS3D&amp;type=0&amp;section_id=101&amp;section_id2=258&amp;section_id3=403&amp;date=20211123&amp;page=1\" title=\"[외환브리핑]팬데믹 재확산+연준 긴축 우려…환율, 1190원대 상승 재시도\">[외환브리핑]팬데믹 재확산+연준 긴축 우려…환율, 1190원대 상승 재시도</a>","link":"https://finance.naver.com/news/news_read.naver?article_id=0005091756&office_id=018&mode=LSS3D&type=0&section_id=101&section_id2=258&section_id3=403&date=20211123&page=1","retrieved":1637626781960},{"title":"'연임' 파월이 외친 \"인플레\"…금리인상 우려 나스닥 급락[뉴욕마감](종합)","contents":"<a href=\"/news/news_read.naver?article_id=0004673888&amp;office_id=008&amp;mode=LSS3D&amp;type=0&amp;section_id=101&amp;section_id2=258&amp;section_id3=403&amp;date=20211123&amp;page=1\" title=\"'연임' 파월이 외친 &quot;인플레&quot;…금리인상 우려 나스닥 급락[뉴욕마감](종합)\">'연임' 파월이 외친 \"인플레\"…금리인상 우려 나스닥 급락[뉴욕마감](종합)</a>","link":"https://finance.naver.com/news/news_read.naver?article_id=0004673888&office_id=008&mode=LSS3D&type=0&section_id=101&section_id2=258&section_id3=403&date=20211123&page=1","retrieved":1637626781961},{"title":"다시 주가 띄우기 나선 머스크...\"최강세단 중국 출시\"","contents":"<a href=\"/news/news_read.naver?article_id=0000998632&amp;office_id=215&amp;mode=LSS3D&amp;type=0&amp;section_id=101&amp;section_id2=258&amp;section_id3=403&amp;date=20211123&amp;page=1\" title=\"다시 주가 띄우기 나선 머스크...&quot;최강세단 중국 출시&quot;\">다시 주가 띄우기 나선 머스크...\"최강세단 중국 출시\"</a>","link":"https://finance.naver.com/news/news_read.naver?article_id=0000998632&office_id=215&mode=LSS3D&type=0&section_id=101&section_id2=258&section_id3=403&date=20211123&page=1","retrieved":1637622349508}]}